fediboat/__init__.py
fediboat/__main__.py
fediboat/cli.py
fediboat/entities.py
fediboat/screens.py
fediboat/settings.py
fediboat/timeline.tcss
fediboat/api/__init__.py
fediboat/api/auth.py
fediboat/api/timelines.py
fediboat-0.1.0.dist-info/LICENSE
fediboat-0.1.0.dist-info/METADATA
fediboat-0.1.0.dist-info/WHEEL
fediboat-0.1.0.dist-info/entry_points.txt
fediboat-0.1.0.dist-info/top_level.txt
fediboat-0.1.0.dist-info/RECORD
